{
  "version": 3,
  "cmakeMinimumRequired": { "major": 3, "minor": 20, "patch": 0 },
  "configurePresets": [
    {
      "name": "default",
      "displayName": "x64 Release (vcpkg)",
      "generator": "Visual Studio 17 2022",
      "architecture": { "value": "x64", "strategy": "set" },
      "binaryDir": "${sourceDir}/build",
      "cacheVariables": {
        "CMAKE_TOOLCHAIN_FILE": "${sourceDir}/vcpkg/scripts/buildsystems/vcpkg.cmake",
        "CMAKE_BUILD_TYPE": "Release",
        "VCPKG_OVERLAY_TRIPLETS": "${sourceDir}/cmake/triplets",
        "VCPKG_TARGET_TRIPLET": "x64-windows-release"
      }
    },
    {
      "name": "node",
      "displayName": "Node.js N-API (vcpkg)",
      "inherits": "default",
      "cacheVariables": {
        "MEMOIR_BUILD_PYTHON": "OFF",
        "MEMOIR_BUILD_NODE": "ON"
      }
    }
  ],
  "buildPresets": [
    {
      "name": "release",
      "configurePreset": "default",
      "configuration": "Release"
    },
    {
      "name": "node-release",
      "configurePreset": "node",
      "configuration": "Release"
    }
  ]
}
